coreuser/__init__.py
coreuser/asgi.py
coreuser/settings.py
coreuser/urls.py
coreuser/utils.py
coreuser/wsgi.py
users/__init__.py
users/admin.py
users/apps.py
users/models.py
users/serializers.py
users/signals.py
users/tests.py
users/throttles.py
users/urls.py
users/validators.py
users/views.py
users/migrations/0001_initial.py
users/migrations/__init__.py
django_auth_boilerplate-0.1.0.dist-info/METADATA
django_auth_boilerplate-0.1.0.dist-info/WHEEL
django_auth_boilerplate-0.1.0.dist-info/top_level.txt
django_auth_boilerplate-0.1.0.dist-info/RECORD
