Metadata-Version: 2.4
Name: django-auth-boilerplate
Version: 0.1.0
Summary: A clean Django authentication boilerplate with JWT, rate limiting, and custom exception handling.
Home-page: https://github.com/Meekemma/auth-boilerplate.git
Author: Emmanuel Ibe
Author-email: ibehemmanuel32@gmail.com
License: MIT
Project-URL: Bug Tracker, https://github.com/Meekemma/auth-boilerplate.git/issues
Project-URL: Documentation, https://github.com/Meekemma/auth-boilerplate.git#readme
Keywords: django authentication jwt rest framework boilerplate
Classifier: Framework :: Django
Classifier: Framework :: Django :: 5.2
Classifier: Programming Language :: Python :: 3
Classifier: Programming Language :: Python :: 3.9
Classifier: Programming Language :: Python :: 3.10
Classifier: License :: OSI Approved :: MIT License
Classifier: Operating System :: OS Independent
Classifier: Intended Audience :: Developers
Classifier: Development Status :: 3 - Alpha
Classifier: Topic :: Software Development :: Libraries :: Python Modules
Requires-Python: >=3.8
Requires-Dist: Django==5.2.4
Requires-Dist: djangorestframework==3.16.0
Requires-Dist: djangorestframework_simplejwt==5.5.1
Requires-Dist: PyJWT==2.10.1
Requires-Dist: asgiref==3.9.1
Requires-Dist: sqlparse==0.5.3
Requires-Dist: tzdata==2025.2
Dynamic: author
Dynamic: author-email
Dynamic: classifier
Dynamic: description
Dynamic: description-content-type
Dynamic: home-page
Dynamic: keywords
Dynamic: license
Dynamic: project-url
Dynamic: requires-dist
Dynamic: requires-python
Dynamic: summary
